setup.py
develia/__init__.py
develia/ml/__init__.py
develia/ml/preprocessing.py
develia_ml.egg-info/PKG-INFO
develia_ml.egg-info/SOURCES.txt
develia_ml.egg-info/dependency_links.txt
develia_ml.egg-info/top_level.txt