Metadata-Version: 1.2
Name: develia-ml
Version: 0.1.0
Summary: Machine learning utility library
Home-page: UNKNOWN
Author: Antonio Gil Espinosa
Author-email: antonio.gil.espinosa@gmail.com
License: UNKNOWN
Platform: UNKNOWN
Requires-Python: >=3.0
